enedis_odoo_bridge/DataMerger.py
enedis_odoo_bridge/EnedisFluxEngine.py
enedis_odoo_bridge/OdooAPI.py
enedis_odoo_bridge/__init__.py
enedis_odoo_bridge/skeleton.py
enedis_odoo_bridge/utils.py
enedis_odoo_bridge/consumption_estimators/__init__.py
enedis_odoo_bridge/consumption_estimators/base_estimator.py
enedis_odoo_bridge/consumption_estimators/last_first_estimator.py
enedis_odoo_bridge/consumption_estimators/soustraction_estimator.py
enedis_odoo_bridge/flux_transformers/__init__.py
enedis_odoo_bridge/flux_transformers/base_flux_transformer.py
enedis_odoo_bridge/flux_transformers/f15_flux_transformer.py
enedis_odoo_bridge/flux_transformers/flux_transformer_factory.py
enedis_odoo_bridge/flux_transformers/r15_flux_transformer.py
enedis_odoo_bridge/processes/__init__.py
enedis_odoo_bridge/processes/add_enedis_service_to_draft_invoice_process.py
enedis_odoo_bridge/processes/base_process.py
enedis_odoo_bridge/processes/update_values_in_draft_invoices_process.py
enedis_odoo_bridge-1.0.1.post1.dev0.dist-info/LICENSE.txt
enedis_odoo_bridge-1.0.1.post1.dev0.dist-info/METADATA
enedis_odoo_bridge-1.0.1.post1.dev0.dist-info/WHEEL
enedis_odoo_bridge-1.0.1.post1.dev0.dist-info/top_level.txt
enedis_odoo_bridge-1.0.1.post1.dev0.dist-info/RECORD
