Metadata-Version: 2.1
Name: enedis_odoo_bridge
Version: 1.0.1.post1.dev0
Summary: Automate enedis flux parsing, then inject data into odoo
Home-page: https://github.com/Virgile-Dauge/enedis_odoo_bridge
Author: Virgile
Author-email: virgile.dauge@pm.me
License: GPL-3.0-only
Project-URL: Documentation, https://pyscaffold.org/
Platform: any
Classifier: Development Status :: 4 - Beta
Classifier: Programming Language :: Python
Requires-Python: >=3.10
License-File: LICENSE.txt
Requires-Dist: importlib-metadata ==4.6.4
Requires-Dist: numpy ==1.23.5
Requires-Dist: pandas ==1.5.2
Requires-Dist: pycryptodome ==3.20.0
Requires-Dist: pytest ==8.1.1
Requires-Dist: python-dotenv ==1.0.1
Requires-Dist: rich ==13.7.1
Requires-Dist: setuptools ==59.6.0
Requires-Dist: sftpretty ==1.1.4
Requires-Dist: Sphinx ==5.0.2
Requires-Dist: xmltodict ==0.13.0
Requires-Dist: xmlschema ==3.3.0
Provides-Extra: testing
Requires-Dist: setuptools ; extra == 'testing'
Requires-Dist: pytest ; extra == 'testing'
Requires-Dist: pytest-cov ; extra == 'testing'
